.VERSION
AUTHORS.rst
CONTRIBUTING.rst
HISTORY.rst
LICENSE
MANIFEST.in
Pipfile
Pipfile.lock
README.rst
USAGE.rst
dev-requirements.txt
requirements.txt
setup.cfg
setup.py
docs/Makefile
docs/authors.rst
docs/conf.py
docs/contributing.rst
docs/history.rst
docs/index.rst
docs/installation.rst
docs/readme.rst
docs/usage.rst
ynabintegrationslib/.VERSION
ynabintegrationslib/AUTHORS.rst
ynabintegrationslib/CONTRIBUTING.rst
ynabintegrationslib/HISTORY.rst
ynabintegrationslib/LICENSE
ynabintegrationslib/Pipfile
ynabintegrationslib/Pipfile.lock
ynabintegrationslib/README.rst
ynabintegrationslib/USAGE.rst
ynabintegrationslib/__init__.py
ynabintegrationslib/_version.py
ynabintegrationslib/dev-requirements.txt
ynabintegrationslib/requirements.txt
ynabintegrationslib/ynabintegrationslib.py
ynabintegrationslib/ynabintegrationslibexceptions.py
ynabintegrationslib.egg-info/PKG-INFO
ynabintegrationslib.egg-info/SOURCES.txt
ynabintegrationslib.egg-info/dependency_links.txt
ynabintegrationslib.egg-info/not-zip-safe
ynabintegrationslib.egg-info/requires.txt
ynabintegrationslib.egg-info/top_level.txt
ynabintegrationslib/adapters/__init__.py
ynabintegrationslib/adapters/abnamro.py
ynabintegrationslib/lib/__init__.py
ynabintegrationslib/lib/core.py