Metadata-Version: 2.1
Name: ynabintegrationslib
Version: 0.2.0
Summary: A library implementing integrations for ABN Amro accounts, ICS credit cards and RABO Bank csv exports with YNAB
Home-page: https://github.com/costastf/ynabintegrationslib
Author: Costas Tyfoxylos
Author-email: costas.tyf@gmail.com
License: MIT
Keywords: ynabintegrationslib ynab abn amro rabobank
Platform: UNKNOWN
Classifier: Development Status :: 4 - Beta
Classifier: Intended Audience :: Developers
Classifier: License :: OSI Approved :: MIT License
Classifier: Natural Language :: English
Classifier: Programming Language :: Python :: 3.7
License-File: LICENSE
License-File: AUTHORS.rst
